seirplus_es/FARZ.py
seirplus_es/__init__.py
seirplus_es/__main__.py
seirplus_es/feed.py
seirplus_es/legacy_models.py
seirplus_es/models.py
seirplus_es/networks.py
seirplus_es/sim_loops.py
seirplus_es/utilities.py
seirplus_es-1.0.1.dist-info/Licence.txt
seirplus_es-1.0.1.dist-info/METADATA
seirplus_es-1.0.1.dist-info/WHEEL
seirplus_es-1.0.1.dist-info/top_level.txt
seirplus_es-1.0.1.dist-info/RECORD
