Metadata-Version: 2.1
Name: seirplus-es
Version: 1.0.1
Summary: Este paquete utiliza un modelo epidemiológico SEIR y redes de contactos (network) para modelar el comportamiento de la pandemia de covid-19. Está basado en el modelo creado por Ryan McGee con modificaciones hechas para ajustarlo a las condiciones específicas de El Salvador.
Home-page: https://github.com/Neik8314/seirsplus_es
Author: Victor Sandoval
Author-email: victor.e.sandoval@gmail.com
License: MIT
Platform: UNKNOWN
Classifier: License :: OSI Approved :: MIT License
Classifier: Programming Language :: Python :: 3
Classifier: Programming Language :: Python :: 3.7
